setup.py
aayush_distributions/Binomialdistribution.py
aayush_distributions/Gaussiandistribution.py
aayush_distributions/Generaldistribution.py
aayush_distributions/__init__.py
aayush_distributions.egg-info/PKG-INFO
aayush_distributions.egg-info/SOURCES.txt
aayush_distributions.egg-info/dependency_links.txt
aayush_distributions.egg-info/not-zip-safe
aayush_distributions.egg-info/top_level.txt